{
  "label": "fullpick_80cargo_4zone_10agv",
  "notes": "Full pickup: 1 cargo per pickup slot (80 points 0100-0179), delivered round-robin evenly across 4 dropoff zones (â/aa/b/bbb, 20 each). v7-bidir. Zone ids regenerated from live DB.",
  "cargos": [
    {
      "atMs": 0,
      "sourcePointName": "0100",
      "destinationZoneId": "21ccd4b4-eab2-4fa0-8c5d-93ea697d17a5"
    },
    {
      "atMs": 0,
      "sourcePointName": "0101",
      "destinationZoneId": "d36c73a8-bbff-4f91-bcce-be87b79883c1"
    },
    {
      "atMs": 0,
      "sourcePointName": "0102",
      "destinationZoneId": "1f1acde2-3846-4bb7-8bcf-badf82715046"
    },
    {
      "atMs": 0,
      "sourcePointName": "0103",
      "destinationZoneId": "18098f7b-dbab-4dae-9fce-7c2ab48fd3f2"
    },
    {
      "atMs": 0,
      "sourcePointName": "0104",
      "destinationZoneId": "21ccd4b4-eab2-4fa0-8c5d-93ea697d17a5"
    },
    {
      "atMs": 0,
      "sourcePointName": "0105",
      "destinationZoneId": "d36c73a8-bbff-4f91-bcce-be87b79883c1"
    },
    {
      "atMs": 0,
      "sourcePointName": "0106",
      "destinationZoneId": "1f1acde2-3846-4bb7-8bcf-badf82715046"
    },
    {
      "atMs": 0,
      "sourcePointName": "0107",
      "destinationZoneId": "18098f7b-dbab-4dae-9fce-7c2ab48fd3f2"
    },
    {
      "atMs": 0,
      "sourcePointName": "0108",
      "destinationZoneId": "21ccd4b4-eab2-4fa0-8c5d-93ea697d17a5"
    },
    {
      "atMs": 0,
      "sourcePointName": "0109",
      "destinationZoneId": "d36c73a8-bbff-4f91-bcce-be87b79883c1"
    },
    {
      "atMs": 0,
      "sourcePointName": "0110",
      "destinationZoneId": "1f1acde2-3846-4bb7-8bcf-badf82715046"
    },
    {
      "atMs": 0,
      "sourcePointName": "0111",
      "destinationZoneId": "18098f7b-dbab-4dae-9fce-7c2ab48fd3f2"
    },
    {
      "atMs": 0,
      "sourcePointName": "0112",
      "destinationZoneId": "21ccd4b4-eab2-4fa0-8c5d-93ea697d17a5"
    },
    {
      "atMs": 0,
      "sourcePointName": "0113",
      "destinationZoneId": "d36c73a8-bbff-4f91-bcce-be87b79883c1"
    },
    {
      "atMs": 0,
      "sourcePointName": "0114",
      "destinationZoneId": "1f1acde2-3846-4bb7-8bcf-badf82715046"
    },
    {
      "atMs": 0,
      "sourcePointName": "0115",
      "destinationZoneId": "18098f7b-dbab-4dae-9fce-7c2ab48fd3f2"
    },
    {
      "atMs": 0,
      "sourcePointName": "0116",
      "destinationZoneId": "21ccd4b4-eab2-4fa0-8c5d-93ea697d17a5"
    },
    {
      "atMs": 0,
      "sourcePointName": "0117",
      "destinationZoneId": "d36c73a8-bbff-4f91-bcce-be87b79883c1"
    },
    {
      "atMs": 0,
      "sourcePointName": "0118",
      "destinationZoneId": "1f1acde2-3846-4bb7-8bcf-badf82715046"
    },
    {
      "atMs": 0,
      "sourcePointName": "0119",
      "destinationZoneId": "18098f7b-dbab-4dae-9fce-7c2ab48fd3f2"
    },
    {
      "atMs": 0,
      "sourcePointName": "0120",
      "destinationZoneId": "21ccd4b4-eab2-4fa0-8c5d-93ea697d17a5"
    },
    {
      "atMs": 0,
      "sourcePointName": "0121",
      "destinationZoneId": "d36c73a8-bbff-4f91-bcce-be87b79883c1"
    },
    {
      "atMs": 0,
      "sourcePointName": "0122",
      "destinationZoneId": "1f1acde2-3846-4bb7-8bcf-badf82715046"
    },
    {
      "atMs": 0,
      "sourcePointName": "0123",
      "destinationZoneId": "18098f7b-dbab-4dae-9fce-7c2ab48fd3f2"
    },
    {
      "atMs": 0,
      "sourcePointName": "0124",
      "destinationZoneId": "21ccd4b4-eab2-4fa0-8c5d-93ea697d17a5"
    },
    {
      "atMs": 0,
      "sourcePointName": "0125",
      "destinationZoneId": "d36c73a8-bbff-4f91-bcce-be87b79883c1"
    },
    {
      "atMs": 0,
      "sourcePointName": "0126",
      "destinationZoneId": "1f1acde2-3846-4bb7-8bcf-badf82715046"
    },
    {
      "atMs": 0,
      "sourcePointName": "0127",
      "destinationZoneId": "18098f7b-dbab-4dae-9fce-7c2ab48fd3f2"
    },
    {
      "atMs": 0,
      "sourcePointName": "0128",
      "destinationZoneId": "21ccd4b4-eab2-4fa0-8c5d-93ea697d17a5"
    },
    {
      "atMs": 0,
      "sourcePointName": "0129",
      "destinationZoneId": "d36c73a8-bbff-4f91-bcce-be87b79883c1"
    },
    {
      "atMs": 0,
      "sourcePointName": "0130",
      "destinationZoneId": "1f1acde2-3846-4bb7-8bcf-badf82715046"
    },
    {
      "atMs": 0,
      "sourcePointName": "0131",
      "destinationZoneId": "18098f7b-dbab-4dae-9fce-7c2ab48fd3f2"
    },
    {
      "atMs": 0,
      "sourcePointName": "0132",
      "destinationZoneId": "21ccd4b4-eab2-4fa0-8c5d-93ea697d17a5"
    },
    {
      "atMs": 0,
      "sourcePointName": "0133",
      "destinationZoneId": "d36c73a8-bbff-4f91-bcce-be87b79883c1"
    },
    {
      "atMs": 0,
      "sourcePointName": "0134",
      "destinationZoneId": "1f1acde2-3846-4bb7-8bcf-badf82715046"
    },
    {
      "atMs": 0,
      "sourcePointName": "0135",
      "destinationZoneId": "18098f7b-dbab-4dae-9fce-7c2ab48fd3f2"
    },
    {
      "atMs": 0,
      "sourcePointName": "0136",
      "destinationZoneId": "21ccd4b4-eab2-4fa0-8c5d-93ea697d17a5"
    },
    {
      "atMs": 0,
      "sourcePointName": "0137",
      "destinationZoneId": "d36c73a8-bbff-4f91-bcce-be87b79883c1"
    },
    {
      "atMs": 0,
      "sourcePointName": "0138",
      "destinationZoneId": "1f1acde2-3846-4bb7-8bcf-badf82715046"
    },
    {
      "atMs": 0,
      "sourcePointName": "0139",
      "destinationZoneId": "18098f7b-dbab-4dae-9fce-7c2ab48fd3f2"
    },
    {
      "atMs": 0,
      "sourcePointName": "0140",
      "destinationZoneId": "21ccd4b4-eab2-4fa0-8c5d-93ea697d17a5"
    },
    {
      "atMs": 0,
      "sourcePointName": "0141",
      "destinationZoneId": "d36c73a8-bbff-4f91-bcce-be87b79883c1"
    },
    {
      "atMs": 0,
      "sourcePointName": "0142",
      "destinationZoneId": "1f1acde2-3846-4bb7-8bcf-badf82715046"
    },
    {
      "atMs": 0,
      "sourcePointName": "0143",
      "destinationZoneId": "18098f7b-dbab-4dae-9fce-7c2ab48fd3f2"
    },
    {
      "atMs": 0,
      "sourcePointName": "0144",
      "destinationZoneId": "21ccd4b4-eab2-4fa0-8c5d-93ea697d17a5"
    },
    {
      "atMs": 0,
      "sourcePointName": "0145",
      "destinationZoneId": "d36c73a8-bbff-4f91-bcce-be87b79883c1"
    },
    {
      "atMs": 0,
      "sourcePointName": "0146",
      "destinationZoneId": "1f1acde2-3846-4bb7-8bcf-badf82715046"
    },
    {
      "atMs": 0,
      "sourcePointName": "0147",
      "destinationZoneId": "18098f7b-dbab-4dae-9fce-7c2ab48fd3f2"
    },
    {
      "atMs": 0,
      "sourcePointName": "0148",
      "destinationZoneId": "21ccd4b4-eab2-4fa0-8c5d-93ea697d17a5"
    },
    {
      "atMs": 0,
      "sourcePointName": "0149",
      "destinationZoneId": "d36c73a8-bbff-4f91-bcce-be87b79883c1"
    },
    {
      "atMs": 0,
      "sourcePointName": "0150",
      "destinationZoneId": "1f1acde2-3846-4bb7-8bcf-badf82715046"
    },
    {
      "atMs": 0,
      "sourcePointName": "0151",
      "destinationZoneId": "18098f7b-dbab-4dae-9fce-7c2ab48fd3f2"
    },
    {
      "atMs": 0,
      "sourcePointName": "0152",
      "destinationZoneId": "21ccd4b4-eab2-4fa0-8c5d-93ea697d17a5"
    },
    {
      "atMs": 0,
      "sourcePointName": "0153",
      "destinationZoneId": "d36c73a8-bbff-4f91-bcce-be87b79883c1"
    },
    {
      "atMs": 0,
      "sourcePointName": "0154",
      "destinationZoneId": "1f1acde2-3846-4bb7-8bcf-badf82715046"
    },
    {
      "atMs": 0,
      "sourcePointName": "0155",
      "destinationZoneId": "18098f7b-dbab-4dae-9fce-7c2ab48fd3f2"
    },
    {
      "atMs": 0,
      "sourcePointName": "0156",
      "destinationZoneId": "21ccd4b4-eab2-4fa0-8c5d-93ea697d17a5"
    },
    {
      "atMs": 0,
      "sourcePointName": "0157",
      "destinationZoneId": "d36c73a8-bbff-4f91-bcce-be87b79883c1"
    },
    {
      "atMs": 0,
      "sourcePointName": "0158",
      "destinationZoneId": "1f1acde2-3846-4bb7-8bcf-badf82715046"
    },
    {
      "atMs": 0,
      "sourcePointName": "0159",
      "destinationZoneId": "18098f7b-dbab-4dae-9fce-7c2ab48fd3f2"
    },
    {
      "atMs": 0,
      "sourcePointName": "0160",
      "destinationZoneId": "21ccd4b4-eab2-4fa0-8c5d-93ea697d17a5"
    },
    {
      "atMs": 0,
      "sourcePointName": "0161",
      "destinationZoneId": "d36c73a8-bbff-4f91-bcce-be87b79883c1"
    },
    {
      "atMs": 0,
      "sourcePointName": "0162",
      "destinationZoneId": "1f1acde2-3846-4bb7-8bcf-badf82715046"
    },
    {
      "atMs": 0,
      "sourcePointName": "0163",
      "destinationZoneId": "18098f7b-dbab-4dae-9fce-7c2ab48fd3f2"
    },
    {
      "atMs": 0,
      "sourcePointName": "0164",
      "destinationZoneId": "21ccd4b4-eab2-4fa0-8c5d-93ea697d17a5"
    },
    {
      "atMs": 0,
      "sourcePointName": "0165",
      "destinationZoneId": "d36c73a8-bbff-4f91-bcce-be87b79883c1"
    },
    {
      "atMs": 0,
      "sourcePointName": "0166",
      "destinationZoneId": "1f1acde2-3846-4bb7-8bcf-badf82715046"
    },
    {
      "atMs": 0,
      "sourcePointName": "0167",
      "destinationZoneId": "18098f7b-dbab-4dae-9fce-7c2ab48fd3f2"
    },
    {
      "atMs": 0,
      "sourcePointName": "0168",
      "destinationZoneId": "21ccd4b4-eab2-4fa0-8c5d-93ea697d17a5"
    },
    {
      "atMs": 0,
      "sourcePointName": "0169",
      "destinationZoneId": "d36c73a8-bbff-4f91-bcce-be87b79883c1"
    },
    {
      "atMs": 0,
      "sourcePointName": "0170",
      "destinationZoneId": "1f1acde2-3846-4bb7-8bcf-badf82715046"
    },
    {
      "atMs": 0,
      "sourcePointName": "0171",
      "destinationZoneId": "18098f7b-dbab-4dae-9fce-7c2ab48fd3f2"
    },
    {
      "atMs": 0,
      "sourcePointName": "0172",
      "destinationZoneId": "21ccd4b4-eab2-4fa0-8c5d-93ea697d17a5"
    },
    {
      "atMs": 0,
      "sourcePointName": "0173",
      "destinationZoneId": "d36c73a8-bbff-4f91-bcce-be87b79883c1"
    },
    {
      "atMs": 0,
      "sourcePointName": "0174",
      "destinationZoneId": "1f1acde2-3846-4bb7-8bcf-badf82715046"
    },
    {
      "atMs": 0,
      "sourcePointName": "0175",
      "destinationZoneId": "18098f7b-dbab-4dae-9fce-7c2ab48fd3f2"
    },
    {
      "atMs": 0,
      "sourcePointName": "0176",
      "destinationZoneId": "21ccd4b4-eab2-4fa0-8c5d-93ea697d17a5"
    },
    {
      "atMs": 0,
      "sourcePointName": "0177",
      "destinationZoneId": "d36c73a8-bbff-4f91-bcce-be87b79883c1"
    },
    {
      "atMs": 0,
      "sourcePointName": "0178",
      "destinationZoneId": "1f1acde2-3846-4bb7-8bcf-badf82715046"
    },
    {
      "atMs": 0,
      "sourcePointName": "0179",
      "destinationZoneId": "18098f7b-dbab-4dae-9fce-7c2ab48fd3f2"
    }
  ]
}
